<?xml version="1.0" encoding="UTF-8"?>
<osm version="0.6" generator="Overpass API 0.7.56.9 76e5016d">
<note>The data included in this document is from www.openstreetmap.org. The data is made available under ODbL.</note>
<meta osm_base="2021-05-14T10:30:57Z" areas="2021-05-14T09:19:34Z"/>

  <node id="8630523419" lat="36.9523408" lon="15.1792022">
    <tag k="access" v="yes"/>
    <tag k="building" v="bunker"/>
    <tag k="bunker_type" v="mg_nest"/>
    <tag k="historic" v="yes"/>
    <tag k="location" v="underground"/>
    <tag k="military" v="bunker"/>
  </node>
  <node id="8723664085" lat="37.0402339" lon="15.3062331">
    <tag k="building" v="bunker"/>
    <tag k="military" v="bunker"/>
  </node>
  <node id="7815978016" lat="37.0592200" lon="15.2931679">
    <tag k="bunker_type" v="bomb_shelter"/>
    <tag k="contact:phone" v="+39 0931 450801"/>
    <tag k="level" v="-1"/>
    <tag k="military" v="bunker"/>
    <tag k="name" v="Ipogeo di piazza Duomo"/>
    <tag k="start_date" v="1629"/>
    <tag k="tourism" v="attraction"/>
    <tag k="wikidata" v="Q16566376"/>
    <tag k="wikipedia" v="it:Ipogeo di piazza Duomo"/>
  </node>
  <node id="8557886889" lat="37.1047580" lon="15.2851336">
    <tag k="building" v="bunker"/>
    <tag k="military" v="bunker"/>
  </node>
  <way id="930828499">
    <center lat="36.9523624" lon="15.1791942"/>
    <nd ref="8630523425"/>
    <nd ref="8630523424"/>
    <nd ref="8630523423"/>
    <nd ref="8630523422"/>
    <nd ref="8630523421"/>
    <nd ref="8630523420"/>
    <nd ref="8630523419"/>
    <nd ref="8630523418"/>
    <nd ref="8630523417"/>
    <nd ref="8630523416"/>
    <nd ref="8630523415"/>
    <nd ref="8630523414"/>
    <nd ref="8630523413"/>
    <nd ref="8630523425"/>
    <tag k="military" v="bunker"/>
  </way>
  <way id="917168184">
    <center lat="36.9790879" lon="15.1749976"/>
    <nd ref="8518756617"/>
    <nd ref="8518750116"/>
    <nd ref="8518750115"/>
    <nd ref="8518750114"/>
    <nd ref="8518750113"/>
    <nd ref="8518750112"/>
    <nd ref="8518750111"/>
    <nd ref="8518756617"/>
    <tag k="building" v="yes"/>
    <tag k="bunker_type" v="pillbox"/>
    <tag k="location" v="overground"/>
    <tag k="military" v="bunker"/>
  </way>
  <way id="813666938">
    <center lat="37.0224891" lon="15.2550973"/>
    <nd ref="7600402137"/>
    <nd ref="7600402136"/>
    <nd ref="7600402135"/>
    <nd ref="7600402134"/>
    <nd ref="7600402133"/>
    <nd ref="7600402132"/>
    <nd ref="7600402131"/>
    <nd ref="7600402137"/>
    <tag k="building" v="yes"/>
    <tag k="bunker_type" v="pillbox"/>
    <tag k="location" v="overground"/>
    <tag k="military" v="bunker"/>
  </way>
  <way id="813666939">
    <center lat="37.0224858" lon="15.2555094"/>
    <nd ref="7600402144"/>
    <nd ref="7600402143"/>
    <nd ref="7600402142"/>
    <nd ref="7600402141"/>
    <nd ref="7600402140"/>
    <nd ref="7600402139"/>
    <nd ref="7600402138"/>
    <nd ref="7600402144"/>
    <tag k="building" v="yes"/>
    <tag k="bunker_type" v="pillbox"/>
    <tag k="location" v="overground"/>
    <tag k="military" v="bunker"/>
  </way>
  <way id="937889174">
    <center lat="37.0035004" lon="15.2690355"/>
    <nd ref="8689084053"/>
    <nd ref="8689084052"/>
    <nd ref="8689084051"/>
    <nd ref="8689084050"/>
    <nd ref="8689084049"/>
    <nd ref="8689084048"/>
    <nd ref="8689084047"/>
    <nd ref="8689084046"/>
    <nd ref="8689084045"/>
    <nd ref="8689084044"/>
    <nd ref="8689084043"/>
    <nd ref="8689084053"/>
    <tag k="building" v="yes"/>
    <tag k="bunker_type" v="pillbox"/>
    <tag k="location" v="overground"/>
    <tag k="military" v="bunker"/>
  </way>
  <way id="937889125">
    <center lat="37.0052339" lon="15.2674965"/>
    <nd ref="8689083800"/>
    <nd ref="8689083799"/>
    <nd ref="8689083798"/>
    <nd ref="8689083797"/>
    <nd ref="8689083796"/>
    <nd ref="8689083795"/>
    <nd ref="8689083794"/>
    <nd ref="8689083793"/>
    <nd ref="8689083792"/>
    <nd ref="8689083791"/>
    <nd ref="8689083790"/>
    <nd ref="8689083800"/>
    <tag k="building" v="yes"/>
    <tag k="bunker_type" v="pillbox"/>
    <tag k="location" v="overground"/>
    <tag k="military" v="bunker"/>
  </way>
  <way id="816344723">
    <center lat="37.0133051" lon="15.2580269"/>
    <nd ref="7624234511"/>
    <nd ref="7624234510"/>
    <nd ref="7624234509"/>
    <nd ref="7624234508"/>
    <nd ref="7624234507"/>
    <nd ref="7624234506"/>
    <nd ref="7624234505"/>
    <nd ref="7624234504"/>
    <nd ref="7624234503"/>
    <nd ref="7624234502"/>
    <nd ref="7624234501"/>
    <nd ref="7624234500"/>
    <nd ref="7624234499"/>
    <nd ref="7624234511"/>
    <tag k="building" v="yes"/>
    <tag k="bunker_type" v="pillbox"/>
    <tag k="location" v="overground"/>
    <tag k="military" v="bunker"/>
  </way>
  <way id="922284990">
    <center lat="37.0112064" lon="15.2759622"/>
    <nd ref="8561965700"/>
    <nd ref="8561965699"/>
    <nd ref="8561965698"/>
    <nd ref="8561965697"/>
    <nd ref="8561965696"/>
    <nd ref="8561965695"/>
    <nd ref="8561965694"/>
    <nd ref="8561965693"/>
    <nd ref="8561965692"/>
    <nd ref="8561965700"/>
    <tag k="building" v="yes"/>
    <tag k="bunker_type" v="pillbox"/>
    <tag k="location" v="overground"/>
    <tag k="military" v="bunker"/>
  </way>
  <way id="932659494">
    <center lat="37.0072018" lon="15.2749175"/>
    <nd ref="8645437941"/>
    <nd ref="8645437940"/>
    <nd ref="8645437939"/>
    <nd ref="8645437938"/>
    <nd ref="8645437937"/>
    <nd ref="8645437936"/>
    <nd ref="8645437935"/>
    <nd ref="8645437934"/>
    <nd ref="8645437933"/>
    <nd ref="8645437932"/>
    <nd ref="8645437931"/>
    <nd ref="8645437941"/>
    <tag k="building" v="yes"/>
    <tag k="bunker_type" v="pillbox"/>
    <tag k="location" v="overground"/>
    <tag k="military" v="bunker"/>
  </way>
  <way id="932659495">
    <center lat="37.0068007" lon="15.2747547"/>
    <nd ref="8645437952"/>
    <nd ref="8645437951"/>
    <nd ref="8645437950"/>
    <nd ref="8645437949"/>
    <nd ref="8645437948"/>
    <nd ref="8645437947"/>
    <nd ref="8645437946"/>
    <nd ref="8645437945"/>
    <nd ref="8645437944"/>
    <nd ref="8645437943"/>
    <nd ref="8645437942"/>
    <nd ref="8645437952"/>
    <tag k="building" v="yes"/>
    <tag k="bunker_type" v="pillbox"/>
    <tag k="location" v="overground"/>
    <tag k="military" v="bunker"/>
  </way>
  <way id="935616655">
    <center lat="37.0059038" lon="15.2835649"/>
    <nd ref="8670009049"/>
    <nd ref="8670009048"/>
    <nd ref="8670009047"/>
    <nd ref="8670009046"/>
    <nd ref="8670009045"/>
    <nd ref="8670009044"/>
    <nd ref="8670009043"/>
    <nd ref="8670009042"/>
    <nd ref="8670009041"/>
    <nd ref="8670009040"/>
    <nd ref="8670009039"/>
    <nd ref="8670009049"/>
    <tag k="building" v="yes"/>
    <tag k="bunker_type" v="pillbox"/>
    <tag k="location" v="overground"/>
    <tag k="military" v="bunker"/>
  </way>
  <way id="820450338">
    <center lat="37.0709937" lon="15.2010896"/>
    <nd ref="7661095204"/>
    <nd ref="7661095203"/>
    <nd ref="7661095202"/>
    <nd ref="7661095201"/>
    <nd ref="7661095200"/>
    <nd ref="7661095199"/>
    <nd ref="7661095198"/>
    <nd ref="7661095204"/>
    <tag k="building" v="yes"/>
    <tag k="bunker_type" v="pillbox"/>
    <tag k="location" v="overground"/>
    <tag k="military" v="bunker"/>
  </way>
  <way id="773605026">
    <center lat="37.1080635" lon="15.1886254"/>
    <nd ref="7221002818"/>
    <nd ref="7221002817"/>
    <nd ref="7221002816"/>
    <nd ref="7221002815"/>
    <nd ref="7221002814"/>
    <nd ref="7221002813"/>
    <nd ref="7221002812"/>
    <nd ref="7221002811"/>
    <nd ref="7221002818"/>
    <tag k="building" v="yes"/>
    <tag k="bunker_type" v="pillbox"/>
    <tag k="location" v="overground"/>
    <tag k="military" v="bunker"/>
  </way>
  <way id="773605027">
    <center lat="37.1080432" lon="15.1888642"/>
    <nd ref="7221002826"/>
    <nd ref="7221002825"/>
    <nd ref="7221002824"/>
    <nd ref="7221002823"/>
    <nd ref="7221002822"/>
    <nd ref="7221002821"/>
    <nd ref="7221002820"/>
    <nd ref="7221002819"/>
    <nd ref="7221002826"/>
    <tag k="building" v="yes"/>
    <tag k="bunker_type" v="pillbox"/>
    <tag k="location" v="overground"/>
    <tag k="military" v="bunker"/>
  </way>
  <way id="916838446">
    <center lat="37.0570447" lon="15.2294513"/>
    <nd ref="8515486407"/>
    <nd ref="8515486406"/>
    <nd ref="8515486405"/>
    <nd ref="8515486404"/>
    <nd ref="8515486403"/>
    <nd ref="8515486402"/>
    <nd ref="8515486401"/>
    <nd ref="8515486400"/>
    <nd ref="8515486399"/>
    <nd ref="8515486398"/>
    <nd ref="8515486397"/>
    <nd ref="8515486396"/>
    <nd ref="8515486395"/>
    <nd ref="8515486407"/>
    <tag k="building" v="yes"/>
    <tag k="bunker_type" v="pillbox"/>
    <tag k="location" v="overground"/>
    <tag k="military" v="bunker"/>
  </way>
  <way id="814017920">
    <center lat="37.0376751" lon="15.2546076"/>
    <nd ref="7603983807"/>
    <nd ref="7603983806"/>
    <nd ref="7603983805"/>
    <nd ref="7603983804"/>
    <nd ref="7603983803"/>
    <nd ref="7603983802"/>
    <nd ref="7603983801"/>
    <nd ref="7603983800"/>
    <nd ref="7603983799"/>
    <nd ref="7603983798"/>
    <nd ref="7603983797"/>
    <nd ref="7603983807"/>
    <tag k="building" v="yes"/>
    <tag k="bunker_type" v="pillbox"/>
    <tag k="location" v="overground"/>
    <tag k="military" v="bunker"/>
  </way>
  <way id="814017921">
    <center lat="37.0381387" lon="15.2552614"/>
    <nd ref="7603983818"/>
    <nd ref="7603983817"/>
    <nd ref="7603983816"/>
    <nd ref="7603983815"/>
    <nd ref="7603983814"/>
    <nd ref="7603983813"/>
    <nd ref="7603983812"/>
    <nd ref="7603983811"/>
    <nd ref="7603983810"/>
    <nd ref="7603983809"/>
    <nd ref="7603983808"/>
    <nd ref="7603983818"/>
    <tag k="building" v="yes"/>
    <tag k="bunker_type" v="pillbox"/>
    <tag k="location" v="overground"/>
    <tag k="military" v="bunker"/>
  </way>
  <way id="824367372">
    <center lat="37.0518924" lon="15.2371936"/>
    <nd ref="7697443036"/>
    <nd ref="7697443035"/>
    <nd ref="7697443034"/>
    <nd ref="7697443033"/>
    <nd ref="7697443032"/>
    <nd ref="7697443031"/>
    <nd ref="7697443030"/>
    <nd ref="7697443029"/>
    <nd ref="7697443028"/>
    <nd ref="7697443027"/>
    <nd ref="7697443036"/>
    <tag k="building" v="yes"/>
    <tag k="bunker_type" v="pillbox"/>
    <tag k="location" v="overground"/>
    <tag k="military" v="bunker"/>
  </way>
  <way id="824367378">
    <center lat="37.0516033" lon="15.2398918"/>
    <nd ref="7697443080"/>
    <nd ref="7697443079"/>
    <nd ref="7697443078"/>
    <nd ref="7697443077"/>
    <nd ref="7697443076"/>
    <nd ref="7697443075"/>
    <nd ref="7697443074"/>
    <nd ref="7697443073"/>
    <nd ref="7697443072"/>
    <nd ref="7697443071"/>
    <nd ref="7697443080"/>
    <tag k="building" v="yes"/>
    <tag k="bunker_type" v="pillbox"/>
    <tag k="location" v="overground"/>
    <tag k="military" v="bunker"/>
  </way>
  <way id="824367380">
    <center lat="37.0542906" lon="15.2385824"/>
    <nd ref="7697443107"/>
    <nd ref="7697443106"/>
    <nd ref="7697443105"/>
    <nd ref="7697443104"/>
    <nd ref="7697443103"/>
    <nd ref="7697443102"/>
    <nd ref="7697443101"/>
    <nd ref="7697443100"/>
    <nd ref="7697443099"/>
    <nd ref="7697443098"/>
    <nd ref="7697443107"/>
    <tag k="building" v="yes"/>
    <tag k="bunker_type" v="pillbox"/>
    <tag k="location" v="overground"/>
    <tag k="military" v="bunker"/>
  </way>
  <way id="916838447">
    <center lat="37.0578924" lon="15.2302547"/>
    <nd ref="8515505120"/>
    <nd ref="8515505119"/>
    <nd ref="8515505118"/>
    <nd ref="8515505117"/>
    <nd ref="8515486416"/>
    <nd ref="8515486415"/>
    <nd ref="8515486414"/>
    <nd ref="8515486413"/>
    <nd ref="8515486412"/>
    <nd ref="8515486411"/>
    <nd ref="8515486410"/>
    <nd ref="8515486409"/>
    <nd ref="8515486408"/>
    <nd ref="8515505120"/>
    <tag k="building" v="yes"/>
    <tag k="bunker_type" v="pillbox"/>
    <tag k="location" v="overground"/>
    <tag k="military" v="bunker"/>
  </way>
  <way id="916838448">
    <center lat="37.0579341" lon="15.2293897"/>
    <nd ref="8515505133"/>
    <nd ref="8515505132"/>
    <nd ref="8515505131"/>
    <nd ref="8515505130"/>
    <nd ref="8515505129"/>
    <nd ref="8515505128"/>
    <nd ref="8515505127"/>
    <nd ref="8515505126"/>
    <nd ref="8515505125"/>
    <nd ref="8515505124"/>
    <nd ref="8515505123"/>
    <nd ref="8515505122"/>
    <nd ref="8515505121"/>
    <nd ref="8515505133"/>
    <tag k="building" v="yes"/>
    <tag k="bunker_type" v="pillbox"/>
    <tag k="location" v="overground"/>
    <tag k="military" v="bunker"/>
  </way>
  <way id="916838449">
    <center lat="37.0576205" lon="15.2292086"/>
    <nd ref="8515505146"/>
    <nd ref="8515505145"/>
    <nd ref="8515505144"/>
    <nd ref="8515505143"/>
    <nd ref="8515505142"/>
    <nd ref="8515505141"/>
    <nd ref="8515505140"/>
    <nd ref="8515505139"/>
    <nd ref="8515505138"/>
    <nd ref="8515505137"/>
    <nd ref="8515505136"/>
    <nd ref="8515505135"/>
    <nd ref="8515505134"/>
    <nd ref="8515505146"/>
    <tag k="building" v="yes"/>
    <tag k="bunker_type" v="pillbox"/>
    <tag k="location" v="overground"/>
    <tag k="military" v="bunker"/>
  </way>
  <way id="825048599">
    <center lat="37.0732601" lon="15.2143833"/>
    <nd ref="7703785137"/>
    <nd ref="7703785136"/>
    <nd ref="7703785135"/>
    <nd ref="7703785128"/>
    <nd ref="7703785134"/>
    <nd ref="7703785133"/>
    <nd ref="7703785132"/>
    <nd ref="7703785131"/>
    <nd ref="7703785130"/>
    <nd ref="7703785129"/>
    <nd ref="7703785137"/>
    <tag k="building" v="yes"/>
    <tag k="bunker_type" v="pillbox"/>
    <tag k="location" v="overground"/>
    <tag k="military" v="bunker"/>
  </way>
  <way id="825048600">
    <center lat="37.0732202" lon="15.2142384"/>
    <nd ref="7703785146"/>
    <nd ref="7703785145"/>
    <nd ref="7703785144"/>
    <nd ref="7703785143"/>
    <nd ref="7703785142"/>
    <nd ref="7703785141"/>
    <nd ref="7703785140"/>
    <nd ref="7703785139"/>
    <nd ref="7703785138"/>
    <nd ref="7703785146"/>
    <tag k="building" v="yes"/>
    <tag k="bunker_type" v="pillbox"/>
    <tag k="location" v="overground"/>
    <tag k="military" v="bunker"/>
  </way>
  <way id="831502204">
    <center lat="37.0740172" lon="15.2141644"/>
    <nd ref="7763220731"/>
    <nd ref="7763220730"/>
    <nd ref="7763220729"/>
    <nd ref="7763220728"/>
    <nd ref="7763220727"/>
    <nd ref="7763220726"/>
    <nd ref="7763220725"/>
    <nd ref="7763220724"/>
    <nd ref="7763220723"/>
    <nd ref="7763220731"/>
    <tag k="building" v="yes"/>
    <tag k="bunker_type" v="pillbox"/>
    <tag k="location" v="overground"/>
    <tag k="military" v="bunker"/>
  </way>
  <way id="831502205">
    <center lat="37.0740140" lon="15.2136200"/>
    <nd ref="7763220740"/>
    <nd ref="7763220739"/>
    <nd ref="7763220738"/>
    <nd ref="7763220737"/>
    <nd ref="7763220736"/>
    <nd ref="7763220735"/>
    <nd ref="7763220734"/>
    <nd ref="7763220733"/>
    <nd ref="7763220732"/>
    <nd ref="7763220740"/>
    <tag k="building" v="yes"/>
    <tag k="bunker_type" v="pillbox"/>
    <tag k="location" v="overground"/>
    <tag k="military" v="bunker"/>
  </way>
  <way id="813666770">
    <center lat="37.0369141" lon="15.2568763"/>
    <nd ref="7600382540"/>
    <nd ref="7600382532"/>
    <nd ref="7600382533"/>
    <nd ref="7600382539"/>
    <nd ref="7600382534"/>
    <nd ref="7600382535"/>
    <nd ref="7600382538"/>
    <nd ref="7600382536"/>
    <nd ref="7600382529"/>
    <nd ref="6522248822"/>
    <nd ref="7600382530"/>
    <nd ref="7600382537"/>
    <nd ref="7600382531"/>
    <nd ref="7600382540"/>
    <tag k="building" v="yes"/>
    <tag k="bunker_type" v="pillbox"/>
    <tag k="location" v="overground"/>
    <tag k="military" v="bunker"/>
  </way>
  <way id="931211975">
    <center lat="37.0392162" lon="15.2581284"/>
    <nd ref="8633646766"/>
    <nd ref="8633646774"/>
    <nd ref="8633646773"/>
    <nd ref="8633646772"/>
    <nd ref="8633646771"/>
    <nd ref="8633646770"/>
    <nd ref="8633646769"/>
    <nd ref="8633646768"/>
    <nd ref="8633646767"/>
    <nd ref="8633646766"/>
    <tag k="building" v="yes"/>
    <tag k="bunker_type" v="pillbox"/>
    <tag k="location" v="overground"/>
    <tag k="military" v="bunker"/>
  </way>
  <way id="723545497">
    <center lat="37.0406093" lon="15.3073583"/>
    <nd ref="6786281142"/>
    <nd ref="6786281141"/>
    <nd ref="6786281140"/>
    <nd ref="6786281139"/>
    <nd ref="6786281138"/>
    <nd ref="6786281137"/>
    <nd ref="6786281136"/>
    <nd ref="6786281135"/>
    <nd ref="6786281134"/>
    <nd ref="6786281133"/>
    <nd ref="6786281132"/>
    <nd ref="6786281142"/>
    <tag k="building" v="bunker"/>
    <tag k="historic" v="bunker"/>
    <tag k="location" v="underground"/>
    <tag k="military" v="bunker"/>
  </way>
  <way id="723545499">
    <center lat="37.0408299" lon="15.3073071"/>
    <nd ref="6786281152"/>
    <nd ref="6786281151"/>
    <nd ref="6786281147"/>
    <nd ref="6786281150"/>
    <nd ref="6786281149"/>
    <nd ref="6786281152"/>
    <tag k="building" v="bunker"/>
    <tag k="description" v="Bunker munizioni"/>
    <tag k="historic" v="bunker"/>
    <tag k="location" v="underground"/>
    <tag k="military" v="bunker"/>
  </way>
  <way id="820450339">
    <center lat="37.1028103" lon="15.2621167"/>
    <nd ref="7661095211"/>
    <nd ref="7661095210"/>
    <nd ref="7661095209"/>
    <nd ref="7661095208"/>
    <nd ref="7661095207"/>
    <nd ref="7661095206"/>
    <nd ref="7661095205"/>
    <nd ref="7661095211"/>
    <tag k="building" v="yes"/>
    <tag k="bunker_type" v="pillbox"/>
    <tag k="location" v="overground"/>
    <tag k="military" v="bunker"/>
  </way>
  <way id="895201571">
    <center lat="37.1036842" lon="15.2772020"/>
    <nd ref="8321045780"/>
    <nd ref="8321045781"/>
    <nd ref="8321045782"/>
    <nd ref="8321045783"/>
    <nd ref="3304766349"/>
    <nd ref="8321045785"/>
    <nd ref="8321045780"/>
    <tag k="building" v="yes"/>
    <tag k="bunker_type" v="pillbox"/>
    <tag k="location" v="overground"/>
    <tag k="military" v="bunker"/>
  </way>
  <way id="921798056">
    <center lat="37.1014292" lon="15.2881503"/>
    <nd ref="8557886879"/>
    <nd ref="8557886880"/>
    <nd ref="3230413624"/>
    <nd ref="3230413609"/>
    <nd ref="8557886879"/>
    <tag k="building" v="bunker"/>
    <tag k="military" v="bunker"/>
    <tag k="name" v="Opera A"/>
  </way>

</osm>
